<?xml version="1.0" encoding="utf-8"?>
<TestSuit Name="Device Managment" Version="0.1">
  <Parameters>
    <TimeOut>100000</TimeOut>
    <Name>6.2.12 NVT SET NTP CONFIGURATION - NTP MANUAL IPV4</Name>
    <Description>
      TODO:
      - any in GetNTP
      - wrong fist GetNTP
    </Description>
  </Parameters>
  <Test ID = "TC.DM.NET.6_2_12.01" ONVIFTestID="6.2.12" Enabled="true">
    <TestName>NVT SET NTP CONFIGURATION - NTP MANUAL IPV4</TestName>
    <Name>Correct response: FromDHCP = true, no NTPManual</Name>
    <Description>
      Check NVT SET NTP CONFIGURATION - NTP MANUAL IPV4 test
      when DUT return correct response
      (FromDHCP = true, no NTPManual).
    </Description>
    <Step id ="1">
      <Command>GetNTP</Command>
      <Response>Normal</Response>
      <ResponseParameters UseAnyNodes="false">
        <NTPInformation>
          <FromDHCP xmlns="http://www.onvif.org/ver10/schema">true</FromDHCP>
        </NTPInformation>
      </ResponseParameters>
    </Step>
    <Step id ="2">
      <Command>SetNTP</Command>
      <Response>Normal</Response>
      <RequestParameters>
        <FromDHCP>False</FromDHCP>
        <NTPManual>IPv4 10.1.1.1</NTPManual>
      </RequestParameters>
    </Step>
    <Step id ="3">
      <Command>GetNTP</Command>
      <Response>Normal</Response>
      <ResponseParameters UseAnyNodes="false">
        <NTPInformation>
          <FromDHCP xmlns="http://www.onvif.org/ver10/schema">false</FromDHCP>
          <NTPManual xmlns="http://www.onvif.org/ver10/schema">
            <Type>IPv4</Type>
            <IPv4Address>10.1.1.1</IPv4Address>
          </NTPManual>
        </NTPInformation>
      </ResponseParameters>
    </Step>
    <Step id ="4">
      <Command>SetNTP</Command>
      <Response>Normal</Response>
      <RequestParameters>
        <FromDHCP>True</FromDHCP>
      </RequestParameters>
    </Step>
  </Test>
  <Test ID = "TC.DM.NET.6_2_12.02" ONVIFTestID="6.2.12" Enabled="true">
    <TestName>NVT SET NTP CONFIGURATION - NTP MANUAL IPV4</TestName>
    <Name>Correct response: FromDHCP = false, no NTPManual</Name>
    <Description>
      Check NVT SET NTP CONFIGURATION - NTP MANUAL IPV4 test
      when DUT return correct response
      (FromDHCP = false, no NTPManual).
    </Description>
    <Step id ="1">
      <Command>GetNTP</Command>
      <Response>Normal</Response>
      <ResponseParameters UseAnyNodes="false">
        <NTPInformation>
          <FromDHCP xmlns="http://www.onvif.org/ver10/schema">false</FromDHCP>
        </NTPInformation>
      </ResponseParameters>
    </Step>
    <Step id ="2">
      <Command>SetNTP</Command>
      <Response>Normal</Response>
      <RequestParameters>
        <FromDHCP>False</FromDHCP>
        <NTPManual>IPv4 10.1.1.1</NTPManual>
      </RequestParameters>
    </Step>
    <Step id ="3">
      <Command>GetNTP</Command>
      <Response>Normal</Response>
      <ResponseParameters UseAnyNodes="false">
        <NTPInformation>
          <FromDHCP xmlns="http://www.onvif.org/ver10/schema">false</FromDHCP>
          <NTPManual xmlns="http://www.onvif.org/ver10/schema">
            <Type>IPv4</Type>
            <IPv4Address>10.1.1.1</IPv4Address>
          </NTPManual>
        </NTPInformation>
      </ResponseParameters>
    </Step>
    <Step id ="4">
      <Command>SetNTP</Command>
      <Response>Normal</Response>
      <RequestParameters>
        <FromDHCP>False</FromDHCP>
      </RequestParameters>
    </Step>
  </Test>
  <Test ID = "TC.DM.NET.6_2_12.03" ONVIFTestID="6.2.12" Enabled="true">
    <TestName>NVT SET NTP CONFIGURATION - NTP MANUAL IPV4</TestName>
    <Name>Correct response: FromDHCP = false, no SearchDomains, several NTPManual IPv4, IPv6 and DNSName</Name>
    <Description>
      Check NVT SET NTP CONFIGURATION - NTP MANUAL IPV4 test
      when DUT return correct response
      (FromDHCP = false, several NTPManual IPv4, IPv6 and DNSName).
    </Description>
    <Step id ="1">
      <Command>GetNTP</Command>
      <Response>Normal</Response>
      <ResponseParameters UseAnyNodes="false">
        <NTPInformation>
          <FromDHCP xmlns="http://www.onvif.org/ver10/schema">false</FromDHCP>
          <NTPManual xmlns="http://www.onvif.org/ver10/schema">
            <Type>IPv4</Type>
            <IPv4Address>192.168.10.11</IPv4Address>
          </NTPManual>
          <NTPManual xmlns="http://www.onvif.org/ver10/schema">
            <Type>IPv6</Type>
            <IPv6Address>2001:db8:85a3::8a2e:370:7335</IPv6Address>
          </NTPManual>
          <NTPManual xmlns="http://www.onvif.org/ver10/schema">
            <Type>DNS</Type>
            <DNSname>DNSname1</DNSname>
          </NTPManual>
          <NTPManual xmlns="http://www.onvif.org/ver10/schema">
            <Type>IPv4</Type>
            <IPv4Address>192.168.10.12</IPv4Address>
          </NTPManual>
          <NTPManual xmlns="http://www.onvif.org/ver10/schema">
            <Type>IPv6</Type>
            <IPv6Address>2001:db8:85a3::8a2e:370:7334</IPv6Address>
          </NTPManual>
          <NTPManual xmlns="http://www.onvif.org/ver10/schema">
            <Type>DNS</Type>
            <DNSname>DNSname2</DNSname>
          </NTPManual>
        </NTPInformation>
      </ResponseParameters>
    </Step>
    <Step id ="2">
      <Command>SetNTP</Command>
      <Response>Normal</Response>
      <RequestParameters>
        <FromDHCP>False</FromDHCP>
        <NTPManual>IPv4 10.1.1.1</NTPManual>
      </RequestParameters>
    </Step>
    <Step id ="3">
      <Command>GetNTP</Command>
      <Response>Normal</Response>
      <ResponseParameters UseAnyNodes="false">
        <NTPInformation>
          <FromDHCP xmlns="http://www.onvif.org/ver10/schema">false</FromDHCP>
          <NTPManual xmlns="http://www.onvif.org/ver10/schema">
            <Type>IPv4</Type>
            <IPv4Address>10.1.1.1</IPv4Address>
          </NTPManual>
        </NTPInformation>
      </ResponseParameters>
    </Step>
    <Step id ="4">
      <Command>SetNTP</Command>
      <Response>Normal</Response>
      <RequestParameters>
        <FromDHCP>False</FromDHCP>
        <NTPManual>IPv4 192.168.10.11</NTPManual>
        <NTPManual>IPv6 2001:db8:85a3::8a2e:370:7335</NTPManual>
        <NTPManual>DNS DNSname1</NTPManual>
        <NTPManual>IPv4 192.168.10.12</NTPManual>
        <NTPManual>IPv6 2001:db8:85a3::8a2e:370:7334</NTPManual>
        <NTPManual>DNS DNSname2</NTPManual>
      </RequestParameters>
    </Step>
  </Test>
  <Test ID = "TC.DM.NET.6_2_12.04" ONVIFTestID="6.2.12" Enabled="true">
    <TestName>NVT SET NTP CONFIGURATION - NTP MANUAL IPV4</TestName>
    <Name>Correct response: FromDHCP = true, no NTPManual, several NTPfromDHCP IPv4, IPv6 and DNSName</Name>
    <Description>
      Check NVT SET NTP CONFIGURATION - NTP MANUAL IPV4 test
      when DUT return correct response
      (FromDHCP = true, no NTPManual, several NTPfromDHCP IPv4, IPv6 and DNSName).
    </Description>
    <Step id ="1">
      <Command>GetNTP</Command>
      <Response>Normal</Response>
      <ResponseParameters UseAnyNodes="false">
        <NTPInformation>
          <FromDHCP xmlns="http://www.onvif.org/ver10/schema">true</FromDHCP>
          <NTPFromDHCP xmlns="http://www.onvif.org/ver10/schema">
            <Type>IPv4</Type>
            <IPv4Address>192.168.10.11</IPv4Address>
          </NTPFromDHCP>
          <NTPFromDHCP xmlns="http://www.onvif.org/ver10/schema">
            <Type>IPv6</Type>
            <IPv6Address>2001:db8:85a3::8a2e:370:7335</IPv6Address>
          </NTPFromDHCP>
          <NTPFromDHCP xmlns="http://www.onvif.org/ver10/schema">
            <Type>DNS</Type>
            <DNSname>DNSname1</DNSname>
          </NTPFromDHCP>
          <NTPFromDHCP xmlns="http://www.onvif.org/ver10/schema">
            <Type>IPv4</Type>
            <IPv4Address>192.168.10.12</IPv4Address>
          </NTPFromDHCP>
          <NTPFromDHCP xmlns="http://www.onvif.org/ver10/schema">
            <Type>IPv6</Type>
            <IPv6Address>2001:db8:85a3::8a2e:370:7334</IPv6Address>
          </NTPFromDHCP>
          <NTPFromDHCP xmlns="http://www.onvif.org/ver10/schema">
            <Type>DNS</Type>
            <DNSname>DNSname2</DNSname>
          </NTPFromDHCP>
      </NTPInformation>
      </ResponseParameters>
    </Step>
    <Step id ="2">
      <Command>SetNTP</Command>
      <Response>Normal</Response>
      <RequestParameters>
        <FromDHCP>False</FromDHCP>
        <NTPManual>IPv4 10.1.1.1</NTPManual>
      </RequestParameters>
    </Step>
    <Step id ="3">
      <Command>GetNTP</Command>
      <Response>Normal</Response>
      <ResponseParameters UseAnyNodes="false">
        <NTPInformation>
          <FromDHCP xmlns="http://www.onvif.org/ver10/schema">false</FromDHCP>
          <NTPManual xmlns="http://www.onvif.org/ver10/schema">
            <Type>IPv4</Type>
            <IPv4Address>10.1.1.1</IPv4Address>
          </NTPManual>
        </NTPInformation>
      </ResponseParameters>
    </Step>
    <Step id ="4">
      <Command>SetNTP</Command>
      <Response>Normal</Response>
      <RequestParameters>
        <FromDHCP>True</FromDHCP>
      </RequestParameters>
    </Step>
  </Test>
  <Test ID = "TC.DM.NET.6_2_12.05" ONVIFTestID="6.2.12" Enabled="true">
    <TestName>NVT SET NTP CONFIGURATION - NTP MANUAL IPV4</TestName>
    <Name>Wrong response: FromDHCP = true</Name>
    <Description>
      Check NVT SET NTP CONFIGURATION - NTP MANUAL IPV4 test
      when DUT return wrong response
      (FromDHCP = true).
    </Description>
    <Step id ="1">
      <Command>GetNTP</Command>
      <Response>Normal</Response>
      <ResponseParameters UseAnyNodes="false">
        <NTPInformation>
          <FromDHCP xmlns="http://www.onvif.org/ver10/schema">true</FromDHCP>
          <NTPFromDHCP xmlns="http://www.onvif.org/ver10/schema">
            <Type>IPv4</Type>
            <IPv4Address>192.168.10.11</IPv4Address>
          </NTPFromDHCP>
          <NTPFromDHCP xmlns="http://www.onvif.org/ver10/schema">
            <Type>IPv6</Type>
            <IPv6Address>2001:db8:85a3::8a2e:370:7335</IPv6Address>
          </NTPFromDHCP>
          <NTPFromDHCP xmlns="http://www.onvif.org/ver10/schema">
            <Type>IPv4</Type>
            <IPv4Address>192.168.10.12</IPv4Address>
          </NTPFromDHCP>
          <NTPFromDHCP xmlns="http://www.onvif.org/ver10/schema">
            <Type>IPv6</Type>
            <IPv6Address>2001:db8:85a3::8a2e:370:7334</IPv6Address>
          </NTPFromDHCP>
        </NTPInformation>
      </ResponseParameters>
    </Step>
    <Step id ="2">
      <Command>SetNTP</Command>
      <Response>Normal</Response>
      <RequestParameters>
        <FromDHCP>False</FromDHCP>
        <NTPManual>IPv4 10.1.1.1</NTPManual>
      </RequestParameters>
    </Step>
    <Step id ="3">
      <Command>GetNTP</Command>
      <Response>Normal</Response>
      <ResponseParameters UseAnyNodes="false">
        <NTPInformation>
          <FromDHCP xmlns="http://www.onvif.org/ver10/schema">true</FromDHCP>
          <NTPManual xmlns="http://www.onvif.org/ver10/schema">
            <Type>IPv4</Type>
            <IPv4Address>10.1.1.1</IPv4Address>
          </NTPManual>
        </NTPInformation>
      </ResponseParameters>
    </Step>
    <!--<Step id ="4">
      <Command>SetNTP</Command>
      <Response>Normal</Response>
      <RequestParameters>
        <FromDHCP>True</FromDHCP>
      </RequestParameters>
    </Step>-->
  </Test>
  <Test ID = "TC.DM.NET.6_2_12.06" ONVIFTestID="6.2.12" Enabled="true">
    <TestName>NVT SET NTP CONFIGURATION - NTP MANUAL IPV4</TestName>
    <Name>Wrong response: NTPManual Type = IPv6</Name>
    <Description>
      Check NVT SET NTP CONFIGURATION - NTP MANUAL IPV4 test
      when DUT return wrong response
      (NTPManual Type = IPv6).
    </Description>
    <Step id ="1">
      <Command>GetNTP</Command>
      <Response>Normal</Response>
      <ResponseParameters UseAnyNodes="false">
        <NTPInformation>
          <FromDHCP xmlns="http://www.onvif.org/ver10/schema">true</FromDHCP>
          <NTPFromDHCP xmlns="http://www.onvif.org/ver10/schema">
            <Type>IPv4</Type>
            <IPv4Address>192.168.10.11</IPv4Address>
          </NTPFromDHCP>
          <NTPFromDHCP xmlns="http://www.onvif.org/ver10/schema">
            <Type>IPv6</Type>
            <IPv6Address>2001:db8:85a3::8a2e:370:7335</IPv6Address>
          </NTPFromDHCP>
          <NTPFromDHCP xmlns="http://www.onvif.org/ver10/schema">
            <Type>IPv4</Type>
            <IPv4Address>192.168.10.12</IPv4Address>
          </NTPFromDHCP>
          <NTPFromDHCP xmlns="http://www.onvif.org/ver10/schema">
            <Type>IPv6</Type>
            <IPv6Address>2001:db8:85a3::8a2e:370:7334</IPv6Address>
          </NTPFromDHCP>
        </NTPInformation>
      </ResponseParameters>
    </Step>
    <Step id ="2">
      <Command>SetNTP</Command>
      <Response>Normal</Response>
      <RequestParameters>
        <FromDHCP>False</FromDHCP>
        <NTPManual>IPv4 10.1.1.1</NTPManual>
      </RequestParameters>
    </Step>
    <Step id ="3">
      <Command>GetNTP</Command>
      <Response>Normal</Response>
      <ResponseParameters UseAnyNodes="false">
        <NTPInformation>
          <FromDHCP xmlns="http://www.onvif.org/ver10/schema">false</FromDHCP>
          <NTPManual xmlns="http://www.onvif.org/ver10/schema">
            <Type>IPv6</Type>
            <IPv4Address>10.1.1.1</IPv4Address>
          </NTPManual>
        </NTPInformation>
      </ResponseParameters>
    </Step>
    <!--<Step id ="4">
      <Command>SetNTP</Command>
      <Response>Normal</Response>
      <RequestParameters>
        <FromDHCP>True</FromDHCP>
      </RequestParameters>
    </Step>-->
  </Test>
  <Test ID = "TC.DM.NET.6_2_12.07" ONVIFTestID="6.2.12" Enabled="true">
    <TestName>NVT SET NTP CONFIGURATION - NTP MANUAL IPV4</TestName>
    <Name>Wrong response: NTPManual Type = DNS</Name>
    <Description>
      Check NVT SET NTP CONFIGURATION - NTP MANUAL IPV4 test
      when DUT return wrong response
      (NTPManual Type = DNS).
    </Description>
    <Step id ="1">
      <Command>GetNTP</Command>
      <Response>Normal</Response>
      <ResponseParameters UseAnyNodes="false">
        <NTPInformation>
          <FromDHCP xmlns="http://www.onvif.org/ver10/schema">true</FromDHCP>
          <NTPFromDHCP xmlns="http://www.onvif.org/ver10/schema">
            <Type>IPv4</Type>
            <IPv4Address>192.168.10.11</IPv4Address>
          </NTPFromDHCP>
          <NTPFromDHCP xmlns="http://www.onvif.org/ver10/schema">
            <Type>IPv6</Type>
            <IPv6Address>2001:db8:85a3::8a2e:370:7335</IPv6Address>
          </NTPFromDHCP>
          <NTPFromDHCP xmlns="http://www.onvif.org/ver10/schema">
            <Type>IPv4</Type>
            <IPv4Address>192.168.10.12</IPv4Address>
          </NTPFromDHCP>
          <NTPFromDHCP xmlns="http://www.onvif.org/ver10/schema">
            <Type>IPv6</Type>
            <IPv6Address>2001:db8:85a3::8a2e:370:7334</IPv6Address>
          </NTPFromDHCP>
        </NTPInformation>
      </ResponseParameters>
    </Step>
    <Step id ="2">
      <Command>SetNTP</Command>
      <Response>Normal</Response>
      <RequestParameters>
        <FromDHCP>False</FromDHCP>
        <NTPManual>IPv4 10.1.1.1</NTPManual>
      </RequestParameters>
    </Step>
    <Step id ="3">
      <Command>GetNTP</Command>
      <Response>Normal</Response>
      <ResponseParameters UseAnyNodes="false">
        <NTPInformation>
          <FromDHCP xmlns="http://www.onvif.org/ver10/schema">false</FromDHCP>
          <NTPManual xmlns="http://www.onvif.org/ver10/schema">
            <Type>DNS</Type>
            <IPv4Address>10.1.1.1</IPv4Address>
          </NTPManual>
        </NTPInformation>
      </ResponseParameters>
    </Step>
    <!--<Step id ="4">
      <Command>SetNTP</Command>
      <Response>Normal</Response>
      <RequestParameters>
        <FromDHCP>True</FromDHCP>
      </RequestParameters>
    </Step>-->
  </Test>
  <Test ID = "TC.DM.NET.6_2_12.08" ONVIFTestID="6.2.12" Enabled="true">
    <TestName>NVT SET NTP CONFIGURATION - NTP MANUAL IPV4</TestName>
    <Test>Wrong response: NTPManual IPv4Address = 10.1.1.2</Test>
    <Description>
      Check NVT SET NTP CONFIGURATION - NTP MANUAL IPV4 test
      when DUT return wrong response
      (NTPManual IPv4Address = 10.1.1.2).
    </Description>
    <Step id ="1">
      <Command>GetNTP</Command>
      <Response>Normal</Response>
      <ResponseParameters UseAnyNodes="false">
        <NTPInformation>
          <FromDHCP xmlns="http://www.onvif.org/ver10/schema">true</FromDHCP>
          <NTPFromDHCP xmlns="http://www.onvif.org/ver10/schema">
            <Type>IPv4</Type>
            <IPv4Address>192.168.10.11</IPv4Address>
          </NTPFromDHCP>
          <NTPFromDHCP xmlns="http://www.onvif.org/ver10/schema">
            <Type>IPv6</Type>
            <IPv6Address>2001:db8:85a3::8a2e:370:7335</IPv6Address>
          </NTPFromDHCP>
          <NTPFromDHCP xmlns="http://www.onvif.org/ver10/schema">
            <Type>IPv4</Type>
            <IPv4Address>192.168.10.12</IPv4Address>
          </NTPFromDHCP>
          <NTPFromDHCP xmlns="http://www.onvif.org/ver10/schema">
            <Type>IPv6</Type>
            <IPv6Address>2001:db8:85a3::8a2e:370:7334</IPv6Address>
          </NTPFromDHCP>
        </NTPInformation>
      </ResponseParameters>
    </Step>
    <Step id ="2">
      <Command>SetNTP</Command>
      <Response>Normal</Response>
      <RequestParameters>
        <FromDHCP>False</FromDHCP>
        <NTPManual>IPv4 10.1.1.1</NTPManual>
      </RequestParameters>
    </Step>
    <Step id ="3">
      <Command>GetNTP</Command>
      <Response>Normal</Response>
      <ResponseParameters UseAnyNodes="false">
        <NTPInformation>
          <FromDHCP xmlns="http://www.onvif.org/ver10/schema">false</FromDHCP>
          <NTPManual xmlns="http://www.onvif.org/ver10/schema">
            <Type>IPv4</Type>
            <IPv4Address>10.1.1.2</IPv4Address>
          </NTPManual>
        </NTPInformation>
      </ResponseParameters>
    </Step>
    <!--<Step id ="4">
      <Command>SetNTP</Command>
      <Response>Normal</Response>
      <RequestParameters>
        <FromDHCP>True</FromDHCP>
      </RequestParameters>
    </Step>-->
  </Test>
  <Test ID = "TC.DM.NET.6_2_12.09" ONVIFTestID="6.2.12" Enabled="true">
    <TestName>NVT SET NTP CONFIGURATION - NTP MANUAL IPV4</TestName>
    <Name>Wrong response: NTPManual IPv6Address instead of IPv4Address</Name>
    <Description>
      Check NVT SET NTP CONFIGURATION - NTP MANUAL IPV4 test
      when DUT return wrong response
      (NTPManual IPv6Address instead of IPv4Address).
    </Description>
    <Step id ="1">
      <Command>GetNTP</Command>
      <Response>Normal</Response>
      <ResponseParameters UseAnyNodes="false">
        <NTPInformation>
          <FromDHCP xmlns="http://www.onvif.org/ver10/schema">true</FromDHCP>
          <NTPFromDHCP xmlns="http://www.onvif.org/ver10/schema">
            <Type>IPv4</Type>
            <IPv4Address>192.168.10.11</IPv4Address>
          </NTPFromDHCP>
          <NTPFromDHCP xmlns="http://www.onvif.org/ver10/schema">
            <Type>IPv6</Type>
            <IPv6Address>2001:db8:85a3::8a2e:370:7335</IPv6Address>
          </NTPFromDHCP>
          <NTPFromDHCP xmlns="http://www.onvif.org/ver10/schema">
            <Type>IPv4</Type>
            <IPv4Address>192.168.10.12</IPv4Address>
          </NTPFromDHCP>
          <NTPFromDHCP xmlns="http://www.onvif.org/ver10/schema">
            <Type>IPv6</Type>
            <IPv6Address>2001:db8:85a3::8a2e:370:7334</IPv6Address>
          </NTPFromDHCP>
        </NTPInformation>
      </ResponseParameters>
    </Step>
    <Step id ="2">
      <Command>SetNTP</Command>
      <Response>Normal</Response>
      <RequestParameters>
        <FromDHCP>False</FromDHCP>
        <NTPManual>IPv4 10.1.1.1</NTPManual>
      </RequestParameters>
    </Step>
    <Step id ="3">
      <Command>GetNTP</Command>
      <Response>Normal</Response>
      <ResponseParameters UseAnyNodes="false">
        <NTPInformation>
          <FromDHCP xmlns="http://www.onvif.org/ver10/schema">false</FromDHCP>
          <NTPManual xmlns="http://www.onvif.org/ver10/schema">
            <Type>IPv4</Type>
            <IPv6Address>10.1.1.1</IPv6Address>
          </NTPManual>
        </NTPInformation>
      </ResponseParameters>
    </Step>
    <!--<Step id ="4">
      <Command>SetNTP</Command>
      <Response>Normal</Response>
      <RequestParameters>
        <FromDHCP>True</FromDHCP>
      </RequestParameters>
    </Step>-->
  </Test>
  <Test ID = "TC.DM.NET.6_2_12.10" ONVIFTestID="6.2.12" Enabled="true">
    <TestName>NVT SET NTP CONFIGURATION - NTP MANUAL IPV4</TestName>
    <Name>Wrong response: NTPManual DNSname instead of IPv4Address</Name>
    <Description>
      Check NVT SET NTP CONFIGURATION - NTP MANUAL IPV4 test
      when DUT return wrong response
      (NTPManual DNSname instead of IPv4Address).
    </Description>
    <Step id ="1">
      <Command>GetNTP</Command>
      <Response>Normal</Response>
      <ResponseParameters UseAnyNodes="false">
        <NTPInformation>
          <FromDHCP xmlns="http://www.onvif.org/ver10/schema">true</FromDHCP>
          <NTPFromDHCP xmlns="http://www.onvif.org/ver10/schema">
            <Type>IPv4</Type>
            <IPv4Address>192.168.10.11</IPv4Address>
          </NTPFromDHCP>
          <NTPFromDHCP xmlns="http://www.onvif.org/ver10/schema">
            <Type>IPv6</Type>
            <IPv6Address>2001:db8:85a3::8a2e:370:7335</IPv6Address>
          </NTPFromDHCP>
          <NTPFromDHCP xmlns="http://www.onvif.org/ver10/schema">
            <Type>IPv4</Type>
            <IPv4Address>192.168.10.12</IPv4Address>
          </NTPFromDHCP>
          <NTPFromDHCP xmlns="http://www.onvif.org/ver10/schema">
            <Type>IPv6</Type>
            <IPv6Address>2001:db8:85a3::8a2e:370:7334</IPv6Address>
          </NTPFromDHCP>
        </NTPInformation>
      </ResponseParameters>
    </Step>
    <Step id ="2">
      <Command>SetNTP</Command>
      <Response>Normal</Response>
      <RequestParameters>
        <FromDHCP>False</FromDHCP>
        <NTPManual>IPv4 10.1.1.1</NTPManual>
      </RequestParameters>
    </Step>
    <Step id ="3">
      <Command>GetNTP</Command>
      <Response>Normal</Response>
      <ResponseParameters UseAnyNodes="false">
        <NTPInformation>
          <FromDHCP xmlns="http://www.onvif.org/ver10/schema">false</FromDHCP>
          <NTPManual xmlns="http://www.onvif.org/ver10/schema">
            <Type>IPv4</Type>
            <DNSname>DNSname1</DNSname>
          </NTPManual>
        </NTPInformation>
      </ResponseParameters>
    </Step>
    <!--<Step id ="4">
      <Command>SetNTP</Command>
      <Response>Normal</Response>
      <RequestParameters>
        <FromDHCP>True</FromDHCP>
      </RequestParameters>
    </Step>-->
  </Test>
  <Test ID = "TC.DM.NET.6_2_12.11" ONVIFTestID="6.2.12" Enabled="true">
    <TestName>NVT SET NTP CONFIGURATION - NTP MANUAL IPV4</TestName>
    <Test>Wrong response: additional NTPManual</Test>
    <Description>
      Check NVT SET NTP CONFIGURATION - NTP MANUAL IPV4 test
      when DUT return wrong response
      (additional NTPManual).
    </Description>
    <Step id ="1">
      <Command>GetNTP</Command>
      <Response>Normal</Response>
      <ResponseParameters UseAnyNodes="false">
        <NTPInformation>
          <FromDHCP xmlns="http://www.onvif.org/ver10/schema">true</FromDHCP>
          <NTPFromDHCP xmlns="http://www.onvif.org/ver10/schema">
            <Type>IPv4</Type>
            <IPv4Address>192.168.10.11</IPv4Address>
          </NTPFromDHCP>
          <NTPFromDHCP xmlns="http://www.onvif.org/ver10/schema">
            <Type>IPv6</Type>
            <IPv6Address>2001:db8:85a3::8a2e:370:7335</IPv6Address>
          </NTPFromDHCP>
          <NTPFromDHCP xmlns="http://www.onvif.org/ver10/schema">
            <Type>IPv4</Type>
            <IPv4Address>192.168.10.12</IPv4Address>
          </NTPFromDHCP>
          <NTPFromDHCP xmlns="http://www.onvif.org/ver10/schema">
            <Type>IPv6</Type>
            <IPv6Address>2001:db8:85a3::8a2e:370:7334</IPv6Address>
          </NTPFromDHCP>
        </NTPInformation>
      </ResponseParameters>
    </Step>
    <Step id ="2">
      <Command>SetNTP</Command>
      <Response>Normal</Response>
      <RequestParameters>
        <FromDHCP>False</FromDHCP>
        <NTPManual>IPv4 10.1.1.1</NTPManual>
      </RequestParameters>
    </Step>
    <Step id ="3">
      <Command>GetNTP</Command>
      <Response>Normal</Response>
      <ResponseParameters UseAnyNodes="false">
        <NTPInformation>
          <FromDHCP xmlns="http://www.onvif.org/ver10/schema">false</FromDHCP>
          <NTPManual xmlns="http://www.onvif.org/ver10/schema">
            <Type>IPv4</Type>
            <IPv4Address>10.1.1.1</IPv4Address>
          </NTPManual>
          <NTPManual xmlns="http://www.onvif.org/ver10/schema">
            <Type>IPv4</Type>
            <IPv4Address>10.1.1.2</IPv4Address>
          </NTPManual>
        </NTPInformation>
      </ResponseParameters>
    </Step>
    <!--<Step id ="4">
      <Command>SetNTP</Command>
      <Response>Normal</Response>
      <RequestParameters>
        <FromDHCP>True</FromDHCP>
      </RequestParameters>
    </Step>-->
  </Test>
  <Test ID = "TC.DM.NET.6_2_12.12" ONVIFTestID="6.2.12" Enabled="true">
    <TestName>NVT SET NTP CONFIGURATION - NTP MANUAL IPV4</TestName>
    <Name>Wrong response: additional NTPfromDHCP</Name>
    <Description>
      Check NVT SET NTP CONFIGURATION - NTP MANUAL IPV4
      test when DUT return wrong response
      (additional NTPfromDHCP).
    </Description>
    <Step id ="1">
      <Command>GetNTP</Command>
      <Response>Normal</Response>
      <ResponseParameters UseAnyNodes="false">
        <NTPInformation>
          <FromDHCP xmlns="http://www.onvif.org/ver10/schema">true</FromDHCP>
          <NTPFromDHCP xmlns="http://www.onvif.org/ver10/schema">
            <Type>IPv4</Type>
            <IPv4Address>192.168.10.11</IPv4Address>
          </NTPFromDHCP>
          <NTPFromDHCP xmlns="http://www.onvif.org/ver10/schema">
            <Type>IPv6</Type>
            <IPv6Address>2001:db8:85a3::8a2e:370:7335</IPv6Address>
          </NTPFromDHCP>
          <NTPFromDHCP xmlns="http://www.onvif.org/ver10/schema">
            <Type>IPv4</Type>
            <IPv4Address>192.168.10.12</IPv4Address>
          </NTPFromDHCP>
          <NTPFromDHCP xmlns="http://www.onvif.org/ver10/schema">
            <Type>IPv6</Type>
            <IPv6Address>2001:db8:85a3::8a2e:370:7334</IPv6Address>
          </NTPFromDHCP>
        </NTPInformation>
      </ResponseParameters>
    </Step>
    <Step id ="2">
      <Command>SetNTP</Command>
      <Response>Normal</Response>
      <RequestParameters>
        <FromDHCP>False</FromDHCP>
        <NTPManual>IPv4 10.1.1.1</NTPManual>
      </RequestParameters>
    </Step>
    <Step id ="3">
      <Command>GetNTP</Command>
      <Response>Normal</Response>
      <ResponseParameters UseAnyNodes="false">
        <NTPInformation>
          <FromDHCP xmlns="http://www.onvif.org/ver10/schema">false</FromDHCP>
          <NTPFromDHCP xmlns="http://www.onvif.org/ver10/schema">
            <Type>IPv4</Type>
            <IPv4Address>10.1.1.1</IPv4Address>
          </NTPFromDHCP>
          <NTPManual xmlns="http://www.onvif.org/ver10/schema">
            <Type>IPv4</Type>
            <IPv4Address>10.1.1.1</IPv4Address>
          </NTPManual>
        </NTPInformation>
      </ResponseParameters>
    </Step>
    <!--<Step id ="4">
      <Command>SetNTP</Command>
      <Response>Normal</Response>
      <RequestParameters>
        <FromDHCP>True</FromDHCP>
      </RequestParameters>
    </Step>-->
  </Test>
  <Test ID = "TC.DM.NET.6_2_12.13" ONVIFTestID="6.2.12" Enabled="true">
    <TestName>NVT SET NTP CONFIGURATION - NTP MANUAL IPV4</TestName>
    <Test>Corect response: additional Extension</Test>
    <Description>
      Check NVT SET NTP CONFIGURATION - NTP MANUAL IPV4 test
      when DUT return correct response
      (additional Extension).
    </Description>
    <Step id ="1">
      <Command>GetNTP</Command>
      <Response>Normal</Response>
      <ResponseParameters UseAnyNodes="false">
        <NTPInformation>
          <FromDHCP xmlns="http://www.onvif.org/ver10/schema">true</FromDHCP>
          <NTPFromDHCP xmlns="http://www.onvif.org/ver10/schema">
            <Type>IPv4</Type>
            <IPv4Address>192.168.10.11</IPv4Address>
          </NTPFromDHCP>
          <NTPFromDHCP xmlns="http://www.onvif.org/ver10/schema">
            <Type>IPv6</Type>
            <IPv6Address>2001:db8:85a3::8a2e:370:7335</IPv6Address>
          </NTPFromDHCP>
          <NTPFromDHCP xmlns="http://www.onvif.org/ver10/schema">
            <Type>IPv4</Type>
            <IPv4Address>192.168.10.12</IPv4Address>
          </NTPFromDHCP>
          <NTPFromDHCP xmlns="http://www.onvif.org/ver10/schema">
            <Type>IPv6</Type>
            <IPv6Address>2001:db8:85a3::8a2e:370:7334</IPv6Address>
          </NTPFromDHCP>
        </NTPInformation>
      </ResponseParameters>
    </Step>
    <Step id ="2">
      <Command>SetNTP</Command>
      <Response>Normal</Response>
      <RequestParameters>
        <FromDHCP>False</FromDHCP>
        <NTPManual>IPv4 10.1.1.1</NTPManual>
      </RequestParameters>
    </Step>
    <Step id ="3">
      <Command>GetNTP</Command>
      <Response>Normal</Response>
      <ResponseParameters UseAnyNodes="false">
        <NTPInformation>
          <FromDHCP xmlns="http://www.onvif.org/ver10/schema">false</FromDHCP>
          <NTPManual xmlns="http://www.onvif.org/ver10/schema">
            <Type>IPv4</Type>
            <IPv4Address>10.1.1.1</IPv4Address>
          </NTPManual>
          <Extension xmlns="http://www.onvif.org/ver10/schema" />
        </NTPInformation>
      </ResponseParameters>
    </Step>
    <Step id ="4">
      <Command>SetNTP</Command>
      <Response>Normal</Response>
      <RequestParameters>
        <FromDHCP>True</FromDHCP>
      </RequestParameters>
    </Step>
  </Test>
  <Test ID = "TC.DM.NET.6_2_12.14" ONVIFTestID="6.2.12" Enabled="true">
    <TestName>NVT SET NTP CONFIGURATION - NTP MANUAL IPV4</TestName>
    <Name>Fault on first request</Name>
    <Description>
      Check NVT SET NTP CONFIGURATION - NTP MANUAL IPV4 test
      when DUT return failt on first request.
    </Description>
    <Step id ="1">
      <Command>GetNTP</Command>
      <Response>Fault</Response>
      <Code>Sender</Code>
      <Subcode>InvalidArgVal</Subcode>
      <Subcode>InvalidIPv6Address</Subcode>
    </Step>
  </Test>
  <Test ID = "TC.DM.NET.6_2_12.15" ONVIFTestID="6.2.12" Enabled="true">
    <TestName>NVT SET NTP CONFIGURATION - NTP MANUAL IPV4</TestName>
    <Name>Fault on second request</Name>
    <Description>
      Check NVT SET NTP CONFIGURATION - NTP MANUAL IPV4 test
      when DUT return fault on second request.
    </Description>
    <Step id ="1">
      <Command>GetNTP</Command>
      <Response>Normal</Response>
      <ResponseParameters UseAnyNodes="false">
        <NTPInformation>
          <FromDHCP xmlns="http://www.onvif.org/ver10/schema">true</FromDHCP>
          <NTPFromDHCP xmlns="http://www.onvif.org/ver10/schema">
            <Type>IPv4</Type>
            <IPv4Address>192.168.10.11</IPv4Address>
          </NTPFromDHCP>
          <NTPFromDHCP xmlns="http://www.onvif.org/ver10/schema">
            <Type>IPv6</Type>
            <IPv6Address>2001:db8:85a3::8a2e:370:7335</IPv6Address>
          </NTPFromDHCP>
          <NTPFromDHCP xmlns="http://www.onvif.org/ver10/schema">
            <Type>IPv4</Type>
            <IPv4Address>192.168.10.12</IPv4Address>
          </NTPFromDHCP>
          <NTPFromDHCP xmlns="http://www.onvif.org/ver10/schema">
            <Type>IPv6</Type>
            <IPv6Address>2001:db8:85a3::8a2e:370:7334</IPv6Address>
          </NTPFromDHCP>
        </NTPInformation>
      </ResponseParameters>
    </Step>
    <Step id ="2">
      <Command>SetNTP</Command>
      <Response>Fault</Response>
      <Code>Sender</Code>
      <Subcode>InvalidArgVal</Subcode>
      <Subcode>InvalidIPv6Address</Subcode>
      <RequestParameters>
        <FromDHCP>False</FromDHCP>
        <NTPManual>IPv4 10.1.1.1</NTPManual>
      </RequestParameters>
    </Step>
  </Test>
  <Test ID = "TC.DM.NET.6_2_12.16" ONVIFTestID="6.2.12" Enabled="true">
    <TestName>NVT SET NTP CONFIGURATION - NTP MANUAL IPV4</TestName>
    <Name>Fault on third request</Name>
    <Description>
      Check NVT SET NTP CONFIGURATION - NTP MANUAL IPV4 test
      when DUT return fault on third request.
    </Description>
    <Step id ="1">
      <Command>GetNTP</Command>
      <Response>Normal</Response>
      <ResponseParameters UseAnyNodes="false">
        <NTPInformation>
          <FromDHCP xmlns="http://www.onvif.org/ver10/schema">true</FromDHCP>
          <NTPFromDHCP xmlns="http://www.onvif.org/ver10/schema">
            <Type>IPv4</Type>
            <IPv4Address>192.168.10.11</IPv4Address>
          </NTPFromDHCP>
          <NTPFromDHCP xmlns="http://www.onvif.org/ver10/schema">
            <Type>IPv6</Type>
            <IPv6Address>2001:db8:85a3::8a2e:370:7335</IPv6Address>
          </NTPFromDHCP>
          <NTPFromDHCP xmlns="http://www.onvif.org/ver10/schema">
            <Type>IPv4</Type>
            <IPv4Address>192.168.10.12</IPv4Address>
          </NTPFromDHCP>
          <NTPFromDHCP xmlns="http://www.onvif.org/ver10/schema">
            <Type>IPv6</Type>
            <IPv6Address>2001:db8:85a3::8a2e:370:7334</IPv6Address>
          </NTPFromDHCP>
        </NTPInformation>
      </ResponseParameters>
    </Step>
    <Step id ="2">
      <Command>SetNTP</Command>
      <Response>Normal</Response>
      <RequestParameters>
        <FromDHCP>False</FromDHCP>
        <NTPManual>IPv4 10.1.1.1</NTPManual>
      </RequestParameters>
    </Step>
    <Step id ="3">
      <Command>GetNTP</Command>
      <Response>Fault</Response>
      <Code>Sender</Code>
      <Subcode>InvalidArgVal</Subcode>
      <Subcode>InvalidIPv6Address</Subcode>
    </Step>
  </Test>
  <Test ID = "TC.DM.NET.6_2_12.17" ONVIFTestID="6.2.12" Enabled="true">
    <TestName>NVT SET NTP CONFIGURATION - NTP MANUAL IPV4</TestName>
    <Name>Fault on fourth request</Name>
    <Description>
      Check NVT SET NTP CONFIGURATION - NTP MANUAL IPV4 test
      when DUT return fault on fourth request.
    </Description>
    <Step id ="1">
      <Command>GetNTP</Command>
      <Response>Normal</Response>
      <ResponseParameters UseAnyNodes="false">
        <NTPInformation>
          <FromDHCP xmlns="http://www.onvif.org/ver10/schema">true</FromDHCP>
          <NTPFromDHCP xmlns="http://www.onvif.org/ver10/schema">
            <Type>IPv4</Type>
            <IPv4Address>192.168.10.11</IPv4Address>
          </NTPFromDHCP>
          <NTPFromDHCP xmlns="http://www.onvif.org/ver10/schema">
            <Type>IPv6</Type>
            <IPv6Address>2001:db8:85a3::8a2e:370:7335</IPv6Address>
          </NTPFromDHCP>
          <NTPFromDHCP xmlns="http://www.onvif.org/ver10/schema">
            <Type>IPv4</Type>
            <IPv4Address>192.168.10.12</IPv4Address>
          </NTPFromDHCP>
          <NTPFromDHCP xmlns="http://www.onvif.org/ver10/schema">
            <Type>IPv6</Type>
            <IPv6Address>2001:db8:85a3::8a2e:370:7334</IPv6Address>
          </NTPFromDHCP>
        </NTPInformation>
      </ResponseParameters>
    </Step>
    <Step id ="2">
      <Command>SetNTP</Command>
      <Response>Normal</Response>
      <RequestParameters>
        <FromDHCP>False</FromDHCP>
        <NTPManual>IPv4 10.1.1.1</NTPManual>
      </RequestParameters>
    </Step>
    <Step id ="3">
      <Command>GetNTP</Command>
      <Response>Normal</Response>
      <ResponseParameters UseAnyNodes="false">
        <NTPInformation>
          <FromDHCP xmlns="http://www.onvif.org/ver10/schema">false</FromDHCP>
          <NTPManual xmlns="http://www.onvif.org/ver10/schema">
            <Type>IPv4</Type>
            <IPv4Address>10.1.1.1</IPv4Address>
          </NTPManual>
          <Extension xmlns="http://www.onvif.org/ver10/schema" />
        </NTPInformation>
      </ResponseParameters>
    </Step>
    <Step id ="4">
      <Command>SetNTP</Command>
      <Response>Fault</Response>
      <Code>Sender</Code>
      <Subcode>InvalidArgVal</Subcode>
      <Subcode>InvalidIPv6Address</Subcode>
      <RequestParameters>
        <FromDHCP>True</FromDHCP>
      </RequestParameters>
    </Step>
  </Test>
  <Test ID = "TC.DM.NET.6_2_12.18" ONVIFTestID="6.2.12" Enabled="true">
    <TestName>NVT SET NTP CONFIGURATION - NTP MANUAL IPV4</TestName>
    <Name>No response on first request</Name>
    <Description>
      Check NVT SET NTP CONFIGURATION - NTP MANUAL IPV4 test
      when DUT return no response on first request.
    </Description>
    <Step id ="1">
      <Command>GetNTP</Command>
      <Response>NoResponse</Response>
    </Step>
  </Test>
  <Test ID = "TC.DM.NET.6_2_12.19" ONVIFTestID="6.2.12" Enabled="true">
    <TestName>NVT SET NTP CONFIGURATION - NTP MANUAL IPV4</TestName>
    <Name>No response on second request</Name>
    <Description>
      Check NVT SET NTP CONFIGURATION - NTP MANUAL IPV4 test
      when DUT return no response on second request.
    </Description>
    <Step id ="1">
      <Command>GetNTP</Command>
      <Response>Normal</Response>
      <ResponseParameters UseAnyNodes="false">
        <NTPInformation>
          <FromDHCP xmlns="http://www.onvif.org/ver10/schema">true</FromDHCP>
          <NTPFromDHCP xmlns="http://www.onvif.org/ver10/schema">
            <Type>IPv4</Type>
            <IPv4Address>192.168.10.11</IPv4Address>
          </NTPFromDHCP>
          <NTPFromDHCP xmlns="http://www.onvif.org/ver10/schema">
            <Type>IPv6</Type>
            <IPv6Address>2001:db8:85a3::8a2e:370:7335</IPv6Address>
          </NTPFromDHCP>
          <NTPFromDHCP xmlns="http://www.onvif.org/ver10/schema">
            <Type>IPv4</Type>
            <IPv4Address>192.168.10.12</IPv4Address>
          </NTPFromDHCP>
          <NTPFromDHCP xmlns="http://www.onvif.org/ver10/schema">
            <Type>IPv6</Type>
            <IPv6Address>2001:db8:85a3::8a2e:370:7334</IPv6Address>
          </NTPFromDHCP>
        </NTPInformation>
      </ResponseParameters>
    </Step>
    <Step id ="2">
      <Command>SetNTP</Command>
      <Response>NoResponse</Response>
      <RequestParameters>
        <FromDHCP>False</FromDHCP>
        <NTPManual>IPv4 10.1.1.1</NTPManual>
      </RequestParameters>
    </Step>
  </Test>
  <Test ID = "TC.DM.NET.6_2_12.20" ONVIFTestID="6.2.12" Enabled="true">
    <TestName>NVT SET NTP CONFIGURATION - NTP MANUAL IPV4</TestName>
    <Name>No response on third request</Name>
    <Description>
      Check NVT SET NTP CONFIGURATION - NTP MANUAL IPV4 test
      when DUT return no response on third request.
    </Description>
    <Step id ="1">
      <Command>GetNTP</Command>
      <Response>Normal</Response>
      <ResponseParameters UseAnyNodes="false">
        <NTPInformation>
          <FromDHCP xmlns="http://www.onvif.org/ver10/schema">true</FromDHCP>
          <NTPFromDHCP xmlns="http://www.onvif.org/ver10/schema">
            <Type>IPv4</Type>
            <IPv4Address>192.168.10.11</IPv4Address>
          </NTPFromDHCP>
          <NTPFromDHCP xmlns="http://www.onvif.org/ver10/schema">
            <Type>IPv6</Type>
            <IPv6Address>2001:db8:85a3::8a2e:370:7335</IPv6Address>
          </NTPFromDHCP>
          <NTPFromDHCP xmlns="http://www.onvif.org/ver10/schema">
            <Type>IPv4</Type>
            <IPv4Address>192.168.10.12</IPv4Address>
          </NTPFromDHCP>
          <NTPFromDHCP xmlns="http://www.onvif.org/ver10/schema">
            <Type>IPv6</Type>
            <IPv6Address>2001:db8:85a3::8a2e:370:7334</IPv6Address>
          </NTPFromDHCP>
        </NTPInformation>
      </ResponseParameters>
    </Step>
    <Step id ="2">
      <Command>SetNTP</Command>
      <Response>Normal</Response>
      <RequestParameters>
        <FromDHCP>False</FromDHCP>
        <NTPManual>IPv4 10.1.1.1</NTPManual>
      </RequestParameters>
    </Step>
    <Step id ="3">
      <Command>GetNTP</Command>
      <Response>NoResponse</Response>
    </Step>
  </Test>
  <Test ID = "TC.DM.NET.6_2_12.21" ONVIFTestID="6.2.12" Enabled="true">
    <TestName>NVT SET NTP CONFIGURATION - NTP MANUAL IPV4</TestName>
    <Name>No response on fourth request</Name>
    <Description>
      Check NVT SET NTP CONFIGURATION - NTP MANUAL IPV4 test
      when DUT return no response on fourth request.
    </Description>
    <Step id ="1">
      <Command>GetNTP</Command>
      <Response>Normal</Response>
      <ResponseParameters UseAnyNodes="false">
        <NTPInformation>
          <FromDHCP xmlns="http://www.onvif.org/ver10/schema">true</FromDHCP>
          <NTPFromDHCP xmlns="http://www.onvif.org/ver10/schema">
            <Type>IPv4</Type>
            <IPv4Address>192.168.10.11</IPv4Address>
          </NTPFromDHCP>
          <NTPFromDHCP xmlns="http://www.onvif.org/ver10/schema">
            <Type>IPv6</Type>
            <IPv6Address>2001:db8:85a3::8a2e:370:7335</IPv6Address>
          </NTPFromDHCP>
          <NTPFromDHCP xmlns="http://www.onvif.org/ver10/schema">
            <Type>IPv4</Type>
            <IPv4Address>192.168.10.12</IPv4Address>
          </NTPFromDHCP>
          <NTPFromDHCP xmlns="http://www.onvif.org/ver10/schema">
            <Type>IPv6</Type>
            <IPv6Address>2001:db8:85a3::8a2e:370:7334</IPv6Address>
          </NTPFromDHCP>
        </NTPInformation>
      </ResponseParameters>
    </Step>
    <Step id ="2">
      <Command>SetNTP</Command>
      <Response>Normal</Response>
      <RequestParameters>
        <FromDHCP>False</FromDHCP>
        <NTPManual>IPv4 10.1.1.1</NTPManual>
      </RequestParameters>
    </Step>
    <Step id ="3">
      <Command>GetNTP</Command>
      <Response>Normal</Response>
      <ResponseParameters UseAnyNodes="false">
        <NTPInformation>
          <FromDHCP xmlns="http://www.onvif.org/ver10/schema">false</FromDHCP>
          <NTPManual xmlns="http://www.onvif.org/ver10/schema">
            <Type>IPv4</Type>
            <IPv4Address>10.1.1.1</IPv4Address>
          </NTPManual>
          <Extension xmlns="http://www.onvif.org/ver10/schema" />
        </NTPInformation>
      </ResponseParameters>
    </Step>
    <Step id ="4">
      <Command>SetNTP</Command>
      <Response>NoResponse</Response>
      <RequestParameters>
        <FromDHCP>True</FromDHCP>
      </RequestParameters>
    </Step>
  </Test>

  <Test ID = "TC.DM.NET.6_2_12.22" ONVIFTestID="6.2.12" Enabled="true">
    <TestName>NVT SET NTP CONFIGURATION - NTP MANUAL IPV4</TestName>
    <Name>Fault on first request (Receiver/ActionNotSupported)</Name>
    <Description>
      Check NVT SET NTP CONFIGURATION - NTP MANUAL IPV4 test
      when DUT return failt on first request (Receiver/ActionNotSupported).
    </Description>
    <Step id ="1">
      <Command>GetNTP</Command>
      <Response>Fault</Response>
      <Code>Receiver</Code>
      <Subcode>ActionNotSupported</Subcode>
    </Step>
  </Test>
  <Test ID = "TC.DM.NET.6_2_12.23" ONVIFTestID="6.2.12" Enabled="true">
    <TestName>NVT SET NTP CONFIGURATION - NTP MANUAL IPV4</TestName>
    <Name>Fault on second request (Receiver/ActionNotSupported)</Name>
    <Description>
      Check NVT SET NTP CONFIGURATION - NTP MANUAL IPV4 test
      when DUT return fault on second request (Receiver/ActionNotSupported).
    </Description>
    <Step id ="1">
      <Command>GetNTP</Command>
      <Response>Normal</Response>
      <ResponseParameters UseAnyNodes="false">
        <NTPInformation>
          <FromDHCP xmlns="http://www.onvif.org/ver10/schema">true</FromDHCP>
          <NTPFromDHCP xmlns="http://www.onvif.org/ver10/schema">
            <Type>IPv4</Type>
            <IPv4Address>192.168.10.11</IPv4Address>
          </NTPFromDHCP>
          <NTPFromDHCP xmlns="http://www.onvif.org/ver10/schema">
            <Type>IPv6</Type>
            <IPv6Address>2001:db8:85a3::8a2e:370:7335</IPv6Address>
          </NTPFromDHCP>
          <NTPFromDHCP xmlns="http://www.onvif.org/ver10/schema">
            <Type>IPv4</Type>
            <IPv4Address>192.168.10.12</IPv4Address>
          </NTPFromDHCP>
          <NTPFromDHCP xmlns="http://www.onvif.org/ver10/schema">
            <Type>IPv6</Type>
            <IPv6Address>2001:db8:85a3::8a2e:370:7334</IPv6Address>
          </NTPFromDHCP>
        </NTPInformation>
      </ResponseParameters>
    </Step>
    <Step id ="2">
      <Command>SetNTP</Command>
      <Response>Fault</Response>
      <Code>Receiver</Code>
      <Subcode>ActionNotSupported</Subcode>
      <RequestParameters>
        <FromDHCP>False</FromDHCP>
        <NTPManual>IPv4 10.1.1.1</NTPManual>
      </RequestParameters>
    </Step>
  </Test>
  <Test ID = "TC.DM.NET.6_2_12.24" ONVIFTestID="6.2.12" Enabled="true">
    <TestName>NVT SET NTP CONFIGURATION - NTP MANUAL IPV4</TestName>
    <Name>Fault on third request (Receiver/ActionNotSupported)</Name>
    <Description>
      Check NVT SET NTP CONFIGURATION - NTP MANUAL IPV4 test
      when DUT return fault on third request (Receiver/ActionNotSupported).
    </Description>
    <Step id ="1">
      <Command>GetNTP</Command>
      <Response>Normal</Response>
      <ResponseParameters UseAnyNodes="false">
        <NTPInformation>
          <FromDHCP xmlns="http://www.onvif.org/ver10/schema">true</FromDHCP>
          <NTPFromDHCP xmlns="http://www.onvif.org/ver10/schema">
            <Type>IPv4</Type>
            <IPv4Address>192.168.10.11</IPv4Address>
          </NTPFromDHCP>
          <NTPFromDHCP xmlns="http://www.onvif.org/ver10/schema">
            <Type>IPv6</Type>
            <IPv6Address>2001:db8:85a3::8a2e:370:7335</IPv6Address>
          </NTPFromDHCP>
          <NTPFromDHCP xmlns="http://www.onvif.org/ver10/schema">
            <Type>IPv4</Type>
            <IPv4Address>192.168.10.12</IPv4Address>
          </NTPFromDHCP>
          <NTPFromDHCP xmlns="http://www.onvif.org/ver10/schema">
            <Type>IPv6</Type>
            <IPv6Address>2001:db8:85a3::8a2e:370:7334</IPv6Address>
          </NTPFromDHCP>
        </NTPInformation>
      </ResponseParameters>
    </Step>
    <Step id ="2">
      <Command>SetNTP</Command>
      <Response>Normal</Response>
      <RequestParameters>
        <FromDHCP>False</FromDHCP>
        <NTPManual>IPv4 10.1.1.1</NTPManual>
      </RequestParameters>
    </Step>
    <Step id ="3">
      <Command>GetNTP</Command>
      <Response>Fault</Response>
      <Code>Receiver</Code>
      <Subcode>ActionNotSupported</Subcode>
    </Step>
  </Test>
  <Test ID = "TC.DM.NET.6_2_12.25" ONVIFTestID="6.2.12" Enabled="true">
    <TestName>NVT SET NTP CONFIGURATION - NTP MANUAL IPV4</TestName>
    <Name>Fault on fourth request (Receiver/ActionNotSupported)</Name>
    <Description>
      Check NVT SET NTP CONFIGURATION - NTP MANUAL IPV4 test
      when DUT return fault on fourth request (Receiver/ActionNotSupported).
    </Description>
    <Step id ="1">
      <Command>GetNTP</Command>
      <Response>Normal</Response>
      <ResponseParameters UseAnyNodes="false">
        <NTPInformation>
          <FromDHCP xmlns="http://www.onvif.org/ver10/schema">true</FromDHCP>
          <NTPFromDHCP xmlns="http://www.onvif.org/ver10/schema">
            <Type>IPv4</Type>
            <IPv4Address>192.168.10.11</IPv4Address>
          </NTPFromDHCP>
          <NTPFromDHCP xmlns="http://www.onvif.org/ver10/schema">
            <Type>IPv6</Type>
            <IPv6Address>2001:db8:85a3::8a2e:370:7335</IPv6Address>
          </NTPFromDHCP>
          <NTPFromDHCP xmlns="http://www.onvif.org/ver10/schema">
            <Type>IPv4</Type>
            <IPv4Address>192.168.10.12</IPv4Address>
          </NTPFromDHCP>
          <NTPFromDHCP xmlns="http://www.onvif.org/ver10/schema">
            <Type>IPv6</Type>
            <IPv6Address>2001:db8:85a3::8a2e:370:7334</IPv6Address>
          </NTPFromDHCP>
        </NTPInformation>
      </ResponseParameters>
    </Step>
    <Step id ="2">
      <Command>SetNTP</Command>
      <Response>Normal</Response>
      <RequestParameters>
        <FromDHCP>False</FromDHCP>
        <NTPManual>IPv4 10.1.1.1</NTPManual>
      </RequestParameters>
    </Step>
    <Step id ="3">
      <Command>GetNTP</Command>
      <Response>Normal</Response>
      <ResponseParameters UseAnyNodes="false">
        <NTPInformation>
          <FromDHCP xmlns="http://www.onvif.org/ver10/schema">false</FromDHCP>
          <NTPManual xmlns="http://www.onvif.org/ver10/schema">
            <Type>IPv4</Type>
            <IPv4Address>10.1.1.1</IPv4Address>
          </NTPManual>
          <Extension xmlns="http://www.onvif.org/ver10/schema" />
        </NTPInformation>
      </ResponseParameters>
    </Step>
    <Step id ="4">
      <Command>SetNTP</Command>
      <Response>Fault</Response>
      <Code>Receiver</Code>
      <Subcode>ActionNotSupported</Subcode>
      <RequestParameters>
        <FromDHCP>True</FromDHCP>
      </RequestParameters>
    </Step>
  </Test>
</TestSuit>
